supermat/__init__.py
supermat/grobid_tokenizer.py
supermat/supermat_tei_parser.py
supermat/utils.py
SuperMat-3.0.0.dist-info/LICENSE
SuperMat-3.0.0.dist-info/METADATA
SuperMat-3.0.0.dist-info/WHEEL
SuperMat-3.0.0.dist-info/top_level.txt
SuperMat-3.0.0.dist-info/RECORD
