Metadata-Version: 2.1
Name: SuperMat
Version: 3.0.0
Summary: SuperMat (Superconductors Material) dataset is a manually **linked** **annotated** dataset of superconductors related materials and properties.
Author-email: Luca Foppiano <lucanoro@duck.com>
Maintainer-email: Luca Foppiano <lucanoro@duck.com>
License: Apache License
Project-URL: Homepage, https://supermat.readthedocs.io
Project-URL: Repository, https://github.com/lfoppiano/supermat
Project-URL: Changelog, https://github.com/lfoppiano/supermat/blob/main/CHANGELOG.md
License-File: LICENSE
